django_queryset_erd/__init__.py
django_queryset_erd/cli.py
django_queryset_erd/generator.py
tests/__init__.py
tests/test_generator.py
tests/test_settings.py
django_queryset_erd-2025.1.1.dist-info/LICENSE
django_queryset_erd-2025.1.1.dist-info/METADATA
django_queryset_erd-2025.1.1.dist-info/WHEEL
django_queryset_erd-2025.1.1.dist-info/top_level.txt
django_queryset_erd-2025.1.1.dist-info/RECORD
