Metadata-Version: 2.2
Name: django-queryset-erd
Version: 2025.1.1
Summary: Generate Entity-Relationship Diagrams from Django querysets
Home-page: https://github.com/josernestodavila/django-queryset-erd
Author: José Ernesto Dávila Pantoja
Author-email: josernestodavila@gmail.com
Classifier: Programming Language :: Python :: 3.12
Classifier: License :: OSI Approved :: MIT License
Classifier: Framework :: Django
Classifier: Intended Audience :: Developers
License-File: LICENSE
Requires-Dist: Django>=4.2
